pydango/__init__.py
pydango/__main__.py
pydango/cinephile.py
pydango/cinephile_sqlite.py
pydango/connection.py
pydango/init_data.py
pydango/primary_func.py
pydango/secondary_func.py
pydango/state.py
pydango/switchlang.py
pydango/tables.py
pydango/theater_owner.py
pydango/theater_owner_sqlite.py
pydango_pip-1.0.2.dist-info/LICENSE
pydango_pip-1.0.2.dist-info/METADATA
pydango_pip-1.0.2.dist-info/WHEEL
pydango_pip-1.0.2.dist-info/entry_points.txt
pydango_pip-1.0.2.dist-info/top_level.txt
pydango_pip-1.0.2.dist-info/RECORD
