Metadata-Version: 2.1
Name: pydango-pip
Version: 1.0.2
Summary: Pip installable database schema that attempts to mimic the Fandango database
Home-page: https://github.com/Captmoonshot/pydango-pip
Author: Sammy Lee
Author-email: sam@gygantor.com
License: MIT
Platform: UNKNOWN
Classifier: License :: OSI Approved :: MIT License
Classifier: Programming Language :: Python :: 3
Classifier: Programming Language :: Python :: 3.7
Requires-Dist: sqlalchemy (==1.3.19)
Requires-Dist: sqlalchemy-utils (==0.36.6)
Requires-Dist: psycopg2-binary (==2.8.6)
Requires-Dist: passlib (==1.7.4)
Requires-Dist: python-dateutil (==2.8.1)
